contador.v
module contador (clk , A, count, rst);
  input clk;
  input count;
  input rst;
  output reg [31:0] A;

always @(negedge clk)
  if (rst)
   A <= 32'h00000000;
  else
     begin
      if (count)
        A <= A + 1;
      else
        A <= A;
     end
endmodule

contador_TB.v
`timescale 1ns / 1ps
`define SIMULATION

module contador_TB;

   reg clk;
   reg count;
   reg rst;
   wire [31:0]A;

   contador uut( .clk(clk) , .A(A) , .count(count) , .rst(rst)  );

   parameter PERIOD          = 20;
   parameter real DUTY_CYCLE = 0.5;
   parameter OFFSET          = 0;

   initial  begin  // Process for clk
     #OFFSET;
     forever
       begin
         clk = 1'b0;
         #(PERIOD-(PERIOD*DUTY_CYCLE)) clk = 1'b1;
         #(PERIOD*DUTY_CYCLE);
       end
   end

   initial begin // Reset the system, Start the image capture process
      rst = 0; count = 0; 
   end

   reg [2:0] i;
   initial begin // Reset the system, Start the image capture process
        #20 rst = 1;
        @ (posedge clk);
        @ (negedge clk);
        rst = 0;
        @ (posedge clk);
        @ (negedge clk);
        count = 1;
       for(i=0; i<10; i=i+1) begin
         @ (posedge clk);
       end
   end


   initial begin: TEST_CASE
     $dumpfile("contador_TB.vcd");
     $dumpvars(-1, uut);
     #(1000) $finish;
   end
endmodule

verilog/contador_TB.vcd
$date
	Mon Apr 20 09:44:36 2026
$end
$version
	Icarus Verilog
$end
$timescale
	1ps
$end
$scope module contador_TB $end
$scope module uut $end
$var wire 1 ! clk $end
$var wire 1 " count $end
$var wire 1 # rst $end
$var reg 32 $ A [31:0] $end
$upscope $end
$upscope $end
$enddefinitions $end
$comment Show the parameter values. $end
$dumpall
$end
#0
$dumpvars
bx $
0#
0"
0!
$end
#10000
1!
#20000
b0 $
0!
1#
#30000
1!
#40000
0#
0!
#50000
1!
#60000
b1 $
1"
0!
#70000
1!
#80000
b10 $
0!
#90000
1!
#100000
b11 $
0!
#110000
1!
#120000
b100 $
0!
#130000
1!
#140000
b101 $
0!
#150000
1!
#160000
b110 $
0!
#170000
1!
#180000
b111 $
0!
#190000
1!
#200000
b1000 $
0!
#210000
1!
#220000
b1001 $
0!
#230000
1!
#240000
b1010 $
0!
#250000
1!
#260000
b1011 $
0!
#270000
1!
#280000
b1100 $
0!
#290000
1!
#300000
b1101 $
0!
#310000
1!
#320000
b1110 $
0!
#330000
1!
#340000
b1111 $
0!
#350000
1!
#360000
b10000 $
0!
#370000
1!
#380000
b10001 $
0!
#390000
1!
#400000
b10010 $
0!
#410000
1!
#420000
b10011 $
0!
#430000
1!
#440000
b10100 $
0!
#450000
1!
#460000
b10101 $
0!
#470000
1!
#480000
b10110 $
0!
#490000
1!
#500000
b10111 $
0!
#510000
1!
#520000
b11000 $
0!
#530000
1!
#540000
b11001 $
0!
#550000
1!
#560000
b11010 $
0!
#570000
1!
#580000
b11011 $
0!
#590000
1!
#600000
b11100 $
0!
#610000
1!
#620000
b11101 $
0!
#630000
1!
#640000
b11110 $
0!
#650000
1!
#660000
b11111 $
0!
#670000
1!
#680000
b100000 $
0!
#690000
1!
#700000
b100001 $
0!
#710000
1!
#720000
b100010 $
0!
#730000
1!
#740000
b100011 $
0!
#750000
1!
#760000
b100100 $
0!
#770000
1!
#780000
b100101 $
0!
#790000
1!
#800000
b100110 $
0!
#810000
1!
#820000
b100111 $
0!
#830000
1!
#840000
b101000 $
0!
#850000
1!
#860000
b101001 $
0!
#870000
1!
#880000
b101010 $
0!
#890000
1!
#900000
b101011 $
0!
#910000
1!
#920000
b101100 $
0!
#930000
1!
#940000
b101101 $
0!
#950000
1!
#960000
b101110 $
0!
#970000
1!
#980000
b101111 $
0!
#990000
1!
#1000000
b110000 $
0!
