verilog/shiftR_32.v
module shiftR_32 (clk , sh, rst, n);
  input clk;
  input sh;
  input rst;
  output reg [31:0] n;

always @(negedge clk)
  if (rst)
   n <= 32'b1 << 5; 
  else
     begin
      if (sh)
        n <= {1'b0,n[31:1]};
      else
        n <= {n[30:0],1'b0};
     end
endmodule

verilog/shiftR_32_TB.v
`timescale 1ns / 1ps
`define SIMULATION

module shiftR_32_TB;

   reg clk;
   reg sh;
   reg rst;
   wire [31:0] n;

   shiftR_32 uut( .clk(clk) , .sh(sh) , .rst(rst) , .n(n) );

   parameter PERIOD          = 20;
   parameter real DUTY_CYCLE = 0.5;
   parameter OFFSET          = 0;

   initial  begin  // Process for clk
     #OFFSET;
     forever
       begin
         clk = 1'b0;
         #(PERIOD-(PERIOD*DUTY_CYCLE)) clk = 1'b1;
         #(PERIOD*DUTY_CYCLE);
       end
   end

   initial begin // Reset the system, Start the image capture process
      rst = 0; sh = 0;
   end

   reg [2:0] i;
   initial begin // Reset the system, Start the image capture process
        rst = 1;
        @ (posedge clk);
        @ (negedge clk);
        rst = 0;
        @ (posedge clk);
        @ (negedge clk);
        sh = 1;
       for(i=0; i<4; i=i+1) begin
         @ (posedge clk);
       end
   end


   initial begin: TEST_CASE
     $dumpfile("shiftR_32_TB.vcd");
     $dumpvars(-1, uut);
     #(1000) $finish;
   end
endmodule

verilog/shiftR_32_TB.vcd
$date
	Sun Apr 19 05:15:06 2026
$end
$version
	Icarus Verilog
$end
$timescale
	1ps
$end
$scope module shiftR_32_TB $end
$scope module uut $end
$var wire 1 ! clk $end
$var wire 1 " rst $end
$var wire 1 # sh $end
$var reg 32 $ n [31:0] $end
$upscope $end
$upscope $end
$enddefinitions $end
$comment Show the parameter values. $end
$dumpall
$end
#0
$dumpvars
b100000 $
0#
1"
0!
$end
#10000
1!
#20000
b1000000 $
0"
0!
#30000
1!
#40000
b100000 $
1#
0!
#50000
1!
#60000
b10000 $
0!
#70000
1!
#80000
b1000 $
0!
#90000
1!
#100000
b100 $
0!
#110000
1!
#120000
b10 $
0!
#130000
1!
#140000
b1 $
0!
#150000
1!
#160000
b0 $
0!
