verilog/control_mult.v
module control_mult( clk , rst , lsb_B , init , z , done , sh , reset , add );

 input clk;
 input rst;
 input lsb_B;
 input init;
 input z;

 output reg done;
 output reg sh;
 output reg reset;
 output reg add;


 parameter START  = 3'b000;
 parameter CHECK_B  = 3'b001;
 parameter CHECK_LSB  = 3'b010;
 parameter SHIFT  = 3'b011;
 parameter ADD    = 3'b100;
 parameter FINISH    = 3'b101;

 reg [2:0] state;

 initial begin
  done  = 0;
  sh    = 0;
  reset = 0;
  add   = 0; 
  state = 0;
 end

always @(posedge clk) begin
    if (rst) begin
      state = START;
    end else begin
    case(state)

      START:begin
        done  <= 0;
        sh    <= 0;
        reset <= 1;
        add   <= 0;
        if(init)
          state = CHECK_B;
        else
          state = START;
      end

     CHECK_B: begin
      done  <= 0;
      sh    <= 0;
      reset <= 0;
      add   <= 0;
      if(z)
        state = CHECK_LSB;
      else
        state = FINISH;
      end

     CHECK_LSB: begin
      done  <= 0;
      sh    <= 0;
      reset <= 0;
      add   <= 0;
      if(lsb_B)
        state = ADD;
      else
        state = SHIFT;
     end

     SHIFT: begin
      done  <= 0;
      sh    <= 1;
      reset <= 0;
      add   <= 0;
      state = CHECK_B;
     end
     ADD: begin
        done  <= 0;
        sh    <= 0;
        reset <= 0;
        add   <= 1;
        state = SHIFT;
     end
     FINISH: begin
        done  <= 1;
        sh    <= 0;
        reset <= 0;
        add   <= 0;
        state = START;
     end

     default: state = START;
   endcase
  end
end

`ifdef BENCH
reg [8*40:1] state_name;
always @(*) begin
  case(state)
    START    : state_name = "START";
    CHECK_B    : state_name = "CHECK_B";
    CHECK_LSB    : state_name = "CHECK_LSB";
    SHIFT    : state_name = "SHIFT";
    ADD      : state_name = "ADD";
    FINISH      : state_name = "FINISH";
  endcase
end
`endif



endmodule

verilog/multiplicador_M/acc.v
module acc (clk , A, add, rst, pp);
  input clk;
  input [31:0]A;
  input add;
  input rst;
  output reg [31:0] pp;

initial pp = 0;

always @(negedge clk)
  if (rst)
   pp <= 32'h00000000;
  else
     begin
      if (add)
        pp <= pp + A;
      else
        pp <= pp;
     end
endmodule

verilog/multiplicador_M/comp.v
module comp(clk, B, z);
  input clk;
  input [15:0]B;
  output reg z;

  always@(*)
    if (B==0)
      z <= 1;
    else
      z <= 0;

endmodule

verilog/multiplicador_M/shiftL_32.v
module shiftL_32 (clk , sh, rst, in_A, s_A);
  input clk;
  input sh;
  input rst;
  input [31:0] in_A;
  output reg [31:0] s_A;

always @(negedge clk)
  if (rst)
   s_A <= {16'b0 , in_A[15:0]};
  else
     begin
      if (sh)
        s_A <= {s_A[30:0],1'b0};
      else
        s_A <= s_A;
     end
endmodule

shiftR_16.v
module shiftR_16 (clk , sh, rst, in_B, s_B);
  input clk;
  input sh;
  input rst;
  input [15:0]in_B;
  output reg [15:0] s_B;

always @(negedge clk)
  if (rst)
    s_B <= in_B;
  else
     begin
      if (sh)
        s_B <= {1'b0,s_B[15:1]};
      else
        s_B <= s_B;
     end
endmodule

verilog/multiplicador_32.v
module multiplicador_32(clk, rst, init, done, A, B, pp);
    input rst;
    input clk;
    input init;
    input [31:0]A;
    input [15:0]B;
    output [31:0]pp;
    output done;

    wire w_sh;
    wire w_reset;
    wire w_acc;
    wire w_z;

    wire [31:0]w_A;
    wire [15:0]w_B;
    shiftR_16 shR0  (.clk(clk) , .sh(w_sh) , .rst(w_reset) , .in_B(B) , .s_B(w_B));
    shiftL_32 shL1  (.clk(clk) , .sh(w_sh) , .rst(w_reset) , .in_A(A) , .s_A(w_A));

    comp comp0 (.B(w_B) , .z(w_z));

    acc acc0 (.clk(clk), .A(w_A) , .add(w_acc) , .rst(w_reset) , .pp(pp));

    control_mult mult0 (.clk(clk) , .rst(rst) , .lsb_B(w_B[0]) , .init(init) , .z(w_z) , .done(done) , .sh(w_sh) , .reset(w_reset) , .add(w_acc));

endmodule

verilog/multiplicador_32_TB.v
`timescale 1ns / 1ps
`define SIMULATION

module multiplicador_32_TB;

 reg clk;
 reg rst;
 reg init;
 reg [31:0]A;
 reg [15:0]B;

 wire done;
 wire [31:0]result;

 multiplicador_32 uut( .clk(clk), .rst(rst), .init(init), .done(done) , .A(A) , .B(B) , .pp(result) );

   parameter PERIOD          = 20;
   parameter real DUTY_CYCLE = 0.5;
   parameter OFFSET          = 0;

   initial  begin  // Process for clk
     #OFFSET;
     forever
       begin
         clk = 1'b0;
         #(PERIOD-(PERIOD*DUTY_CYCLE)) clk = 1'b1;
         #(PERIOD*DUTY_CYCLE);
       end
   end

   initial begin // Reset the system, Start the image capture process
      rst = 1;init = 0; B = 16'b0000000000010111; A = 32'b00000000000000000000000000101100; ;
   end


   reg [2:0] i;
   initial begin // Reset the system, Start the image capture process
        @ (posedge clk);
        @ (negedge clk);
        init = 1;
        rst = 1;
        @ (posedge clk);
        @ (negedge clk);
        rst = 0;
        @(posedge clk);
        @ (posedge clk);
        @ (negedge clk);
        

       end

   initial begin: TEST_CASE
     $dumpfile("multiplicador_32_TB.vcd");
     $dumpvars(-1, uut);
     #(1000) $finish;
   end
endmodule

verilog/multiplicador_M/multiplicador_32_TB.vcd
$date
	Mon May 18 21:23:03 2026
$end
$version
	Icarus Verilog
$end
$timescale
	1ps
$end
$scope module multiplicador_32_TB $end
$scope module uut $end
$var wire 32 ! A [31:0] $end
$var wire 16 " B [15:0] $end
$var wire 1 # clk $end
$var wire 1 $ init $end
$var wire 1 % rst $end
$var wire 1 & w_z $end
$var wire 1 ' w_sh $end
$var wire 1 ( w_reset $end
$var wire 1 ) w_acc $end
$var wire 16 * w_B [15:0] $end
$var wire 32 + w_A [31:0] $end
$var wire 32 , pp [31:0] $end
$var wire 1 - done $end
$scope module acc0 $end
$var wire 1 # clk $end
$var wire 1 ( rst $end
$var wire 1 ) add $end
$var wire 32 . A [31:0] $end
$var reg 32 / pp [31:0] $end
$upscope $end
$scope module comp0 $end
$var wire 1 0 clk $end
$var wire 16 1 B [15:0] $end
$var reg 1 & z $end
$upscope $end
$scope module mult0 $end
$var wire 1 # clk $end
$var wire 1 $ init $end
$var wire 1 2 lsb_B $end
$var wire 1 % rst $end
$var wire 1 & z $end
$var parameter 3 3 ADD $end
$var parameter 3 4 CHECK_B $end
$var parameter 3 5 CHECK_LSB $end
$var parameter 3 6 FINISH $end
$var parameter 3 7 SHIFT $end
$var parameter 3 8 START $end
$var reg 1 ) add $end
$var reg 1 - done $end
$var reg 1 ( reset $end
$var reg 1 ' sh $end
$var reg 3 9 state [2:0] $end
$var reg 320 : state_name [320:1] $end
$upscope $end
$scope module shL1 $end
$var wire 1 # clk $end
$var wire 32 ; in_A [31:0] $end
$var wire 1 ( rst $end
$var wire 1 ' sh $end
$var reg 32 < s_A [31:0] $end
$upscope $end
$scope module shR0 $end
$var wire 1 # clk $end
$var wire 16 = in_B [15:0] $end
$var wire 1 ( rst $end
$var wire 1 ' sh $end
$var reg 16 > s_B [15:0] $end
$upscope $end
$upscope $end
$upscope $end
$enddefinitions $end
$comment Show the parameter values. $end
$dumpall
b0 8
b11 7
b101 6
b10 5
b1 4
b100 3
$end
#0
$dumpvars
bx >
b10111 =
bx <
b101100 ;
b101001101010100010000010101001001010100 :
b0 9
x2
bx 1
z0
b0 /
bx .
0-
b0 ,
bx +
bx *
0)
0(
0'
x&
1%
0$
0#
b10111 "
b101100 !
$end
#10000
1#
#20000
1$
0#
#30000
1#
#40000
0%
0#
#50000
1(
b1000011010010000100010101000011010010110101111101000010 :
b1 9
1#
#60000
0&
12
b101100 +
b101100 .
b101100 <
b10111 *
b10111 1
b10111 >
0#
#70000
0(
b10000110100100001000101010000110100101101011111010011000101001101000010 :
b10 9
1#
#80000
0#
#90000
b10000010100010001000100 :
b100 9
1#
#100000
0#
#110000
1)
b101001101001000010010010100011001010100 :
b11 9
1#
#120000
b101100 ,
b101100 /
0#
#130000
0)
1'
b1000011010010000100010101000011010010110101111101000010 :
b1 9
1#
#140000
b1011000 +
b1011000 .
b1011000 <
b1011 *
b1011 1
b1011 >
0#
#150000
0'
b10000110100100001000101010000110100101101011111010011000101001101000010 :
b10 9
1#
#160000
0#
#170000
b10000010100010001000100 :
b100 9
1#
#180000
0#
#190000
1)
b101001101001000010010010100011001010100 :
b11 9
1#
#200000
b10000100 ,
b10000100 /
0#
#210000
0)
1'
b1000011010010000100010101000011010010110101111101000010 :
b1 9
1#
#220000
b10110000 +
b10110000 .
b10110000 <
b101 *
b101 1
b101 >
0#
#230000
0'
b10000110100100001000101010000110100101101011111010011000101001101000010 :
b10 9
1#
#240000
0#
#250000
b10000010100010001000100 :
b100 9
1#
#260000
0#
#270000
1)
b101001101001000010010010100011001010100 :
b11 9
1#
#280000
b100110100 ,
b100110100 /
0#
#290000
0)
1'
b1000011010010000100010101000011010010110101111101000010 :
b1 9
1#
#300000
02
b101100000 +
b101100000 .
b101100000 <
b10 *
b10 1
b10 >
0#
#310000
0'
b10000110100100001000101010000110100101101011111010011000101001101000010 :
b10 9
1#
#320000
0#
#330000
b101001101001000010010010100011001010100 :
b11 9
1#
#340000
0#
#350000
1'
b1000011010010000100010101000011010010110101111101000010 :
b1 9
1#
#360000
12
b1 *
b1 1
b1 >
b1011000000 +
b1011000000 .
b1011000000 <
0#
#370000
0'
b10000110100100001000101010000110100101101011111010011000101001101000010 :
b10 9
1#
#380000
0#
#390000
b10000010100010001000100 :
b100 9
1#
#400000
0#
#410000
1)
b101001101001000010010010100011001010100 :
b11 9
1#
#420000
b1111110100 ,
b1111110100 /
0#
#430000
0)
1'
b1000011010010000100010101000011010010110101111101000010 :
b1 9
1#
#440000
1&
02
b0 *
b0 1
b0 >
b10110000000 +
b10110000000 .
b10110000000 <
0#
#450000
0'
b10001100100100101001110010010010101001101001000 :
b101 9
1#
#460000
0#
#470000
1-
b101001101010100010000010101001001010100 :
b0 9
1#
#480000
0#
#490000
1(
0-
b1000011010010000100010101000011010010110101111101000010 :
b1 9
1#
#500000
0&
12
b0 ,
b0 /
b101100 +
b101100 .
b101100 <
b10111 *
b10111 1
b10111 >
0#
#510000
0(
b10000110100100001000101010000110100101101011111010011000101001101000010 :
b10 9
1#
#520000
0#
#530000
b10000010100010001000100 :
b100 9
1#
#540000
0#
#550000
1)
b101001101001000010010010100011001010100 :
b11 9
1#
#560000
b101100 ,
b101100 /
0#
#570000
0)
1'
b1000011010010000100010101000011010010110101111101000010 :
b1 9
1#
#580000
b1011000 +
b1011000 .
b1011000 <
b1011 *
b1011 1
b1011 >
0#
#590000
0'
b10000110100100001000101010000110100101101011111010011000101001101000010 :
b10 9
1#
#600000
0#
#610000
b10000010100010001000100 :
b100 9
1#
#620000
0#
#630000
1)
b101001101001000010010010100011001010100 :
b11 9
1#
#640000
b10000100 ,
b10000100 /
0#
#650000
0)
1'
b1000011010010000100010101000011010010110101111101000010 :
b1 9
1#
#660000
b10110000 +
b10110000 .
b10110000 <
b101 *
b101 1
b101 >
0#
#670000
0'
b10000110100100001000101010000110100101101011111010011000101001101000010 :
b10 9
1#
#680000
0#
#690000
b10000010100010001000100 :
b100 9
1#
#700000
0#
#710000
1)
b101001101001000010010010100011001010100 :
b11 9
1#
#720000
b100110100 ,
b100110100 /
0#
#730000
0)
1'
b1000011010010000100010101000011010010110101111101000010 :
b1 9
1#
#740000
02
b101100000 +
b101100000 .
b101100000 <
b10 *
b10 1
b10 >
0#
#750000
0'
b10000110100100001000101010000110100101101011111010011000101001101000010 :
b10 9
1#
#760000
0#
#770000
b101001101001000010010010100011001010100 :
b11 9
1#
#780000
0#
#790000
1'
b1000011010010000100010101000011010010110101111101000010 :
b1 9
1#
#800000
12
b1 *
b1 1
b1 >
b1011000000 +
b1011000000 .
b1011000000 <
0#
#810000
0'
b10000110100100001000101010000110100101101011111010011000101001101000010 :
b10 9
1#
#820000
0#
#830000
b10000010100010001000100 :
b100 9
1#
#840000
0#
#850000
1)
b101001101001000010010010100011001010100 :
b11 9
1#
#860000
b1111110100 ,
b1111110100 /
0#
#870000
0)
1'
b1000011010010000100010101000011010010110101111101000010 :
b1 9
1#
#880000
1&
02
b0 *
b0 1
b0 >
b10110000000 +
b10110000000 .
b10110000000 <
0#
#890000
0'
b10001100100100101001110010010010101001101001000 :
b101 9
1#
#900000
0#
#910000
1-
b101001101010100010000010101001001010100 :
b0 9
1#
#920000
0#
#930000
1(
0-
b1000011010010000100010101000011010010110101111101000010 :
b1 9
1#
#940000
0&
12
b0 ,
b0 /
b101100 +
b101100 .
b101100 <
b10111 *
b10111 1
b10111 >
0#
#950000
0(
b10000110100100001000101010000110100101101011111010011000101001101000010 :
b10 9
1#
#960000
0#
#970000
b10000010100010001000100 :
b100 9
1#
#980000
0#
#990000
1)
b101001101001000010010010100011001010100 :
b11 9
1#
#1000000
b101100 ,
b101100 /
0#
